djfapi/__init__.py
djfapi/base.py
djfapi/exceptions.py
djfapi/enums/__init__.py
djfapi/enums/country_codes.py
djfapi/handlers/__init__.py
djfapi/handlers/error.py
djfapi/middleware/__init__.py
djfapi/middleware/sentry.py
djfapi/models/__init__.py
djfapi/models/user.py
djfapi/patch/__init__.py
djfapi/patch/fastapi.py
djfapi/redis/__init__.py
djfapi/redis/models.py
djfapi/redis/utils.py
djfapi/redis/security/__init__.py
djfapi/redis/security/jwt.py
djfapi/routing/__init__.py
djfapi/routing/base.py
djfapi/routing/django.py
djfapi/routing/registry.py
djfapi/schemas/__init__.py
djfapi/schemas/errors.py
djfapi/schemas/health.py
djfapi/schemas/query.py
djfapi/security/__init__.py
djfapi/security/auth.py
djfapi/security/jwt.py
djfapi/utils/__init__.py
djfapi/utils/fastapi.py
djfapi/utils/fastapi_django.py
djfapi/utils/health_check.py
djfapi/validators/__init__.py
djfapi/validators/language.py
djfapi-0.0.70.dist-info/LICENSE
djfapi-0.0.70.dist-info/METADATA
djfapi-0.0.70.dist-info/WHEEL
djfapi-0.0.70.dist-info/top_level.txt
djfapi-0.0.70.dist-info/RECORD
