Metadata-Version: 2.1
Name: djfapi
Version: 0.0.70
Summary: Utilities for use with FastAPI and django
Home-page: https://github.com/Voltane-EU/djfapi
Author: Manuel Stingl
Author-email: opensource@voltane.eu
License: GNU LGPLv2.1
Classifier: Programming Language :: Python :: 3
Classifier: License :: OSI Approved :: GNU Lesser General Public License v2 or later (LGPLv2+)
Classifier: Operating System :: OS Independent
Classifier: Framework :: Django
Classifier: Framework :: FastAPI
Classifier: Topic :: Utilities
Requires-Python: >=3.9
License-File: LICENSE
Requires-Dist: djdantic >=0.0.23
Requires-Dist: fastapi >=0.63.0
Requires-Dist: django-health-check >=3.16
Requires-Dist: python-forge
Requires-Dist: langcodes
Provides-Extra: redis
Requires-Dist: redis ; extra == 'redis'
